<annotation><folder>labels_xml</folder><filename>124_train.jpg</filename><path>E:/Car-counting/datasets/cars 1/labels_xml/124_train.xml</path><source><database>Unknown</database></source><size><width>1920</width><height>1080</height><depth>3</depth></size><segmented>0</segmented><object><name>_object_</name><pose>Unspecified</pose><truncated>0</truncated><difficult>0</difficult><bndbox><xmin>434</xmin><ymin>138</ymin><xmax>463</xmax><ymax>163</ymax></bndbox></object><object><name>_object_</name><pose>Unspecified</pose><truncated>0</truncated><difficult>0</difficult><bndbox><xmin>468</xmin><ymin>107</ymin><xmax>491</xmax><ymax>119</ymax></bndbox></object><object><name>_object_</name><pose>Unspecified</pose><truncated>0</truncated><difficult>0</difficult><bndbox><xmin>504</xmin><ymin>105</ymin><xmax>524</xmax><ymax>115</ymax></bndbox></object><object><name>_object_</name><pose>Unspecified</pose><truncated>0</truncated><difficult>0</difficult><bndbox><xmin>250</xmin><ymin>125</ymin><xmax>288</xmax><ymax>143</ymax></bndbox></object><object><name>_object_</name><pose>Unspecified</pose><truncated>0</truncated><difficult>0</difficult><bndbox><xmin>301</xmin><ymin>99</ymin><xmax>318</xmax><ymax>109</ymax></bndbox></object><object><name>_object_</name><pose>Unspecified</pose><truncated>0</truncated><difficult>0</difficult><bndbox><xmin>248</xmin><ymin>86</ymin><xmax>258</xmax><ymax>95</ymax></bndbox></object><object><name>_object_</name><pose>Unspecified</pose><truncated>0</truncated><difficult>0</difficult><bndbox><xmin>117</xmin><ymin>118</ymin><xmax>142</xmax><ymax>129</ymax></bndbox></object><object><name>_object_</name><pose>Unspecified</pose><truncated>0</truncated><difficult>0</difficult><bndbox><xmin>145</xmin><ymin>113</ymin><xmax>170</xmax><ymax>125</ymax></bndbox></object><object><name>_object_</name><pose>Unspecified</pose><truncated>0</truncated><difficult>0</difficult><bndbox><xmin>18</xmin><ymin>182</ymin><xmax>61</xmax><ymax>203</ymax></bndbox></object><object><name>_object_</name><pose>Unspecified</pose><truncated>0</truncated><difficult>0</difficult><bndbox><xmin>16</xmin><ymin>172</ymin><xmax>54</xmax><ymax>193</ymax></bndbox></object><object><name>_object_</name><pose>Unspecified</pose><truncated>0</truncated><difficult>0</difficult><bndbox><xmin>21</xmin><ymin>168</ymin><xmax>51</xmax><ymax>177</ymax></bndbox></object><object><name>_object_</name><pose>Unspecified</pose><truncated>0</truncated><difficult>0</difficult><bndbox><xmin>75</xmin><ymin>171</ymin><xmax>125</xmax><ymax>197</ymax></bndbox></object><object><name>_object_</name><pose>Unspecified</pose><truncated>0</truncated><difficult>0</difficult><bndbox><xmin>66</xmin><ymin>168</ymin><xmax>96</xmax><ymax>190</ymax></bndbox></object><object><name>_object_</name><pose>Unspecified</pose><truncated>0</truncated><difficult>0</difficult><bndbox><xmin>72</xmin><ymin>158</ymin><xmax>114</xmax><ymax>174</ymax></bndbox></object></annotation>