<annotation>
	<folder>threecross</folder>
	<filename>472.jpg</filename>
	<path>F:\threecross\472.jpg</path>
	<source>
		<database>Unknown</database>
	</source>
	<size>
		<width>1920</width>
		<height>1080</height>
		<depth>3</depth>
	</size>
	<segmented>0</segmented>
	<object>
		<name>car</name>
		<pose>Unspecified</pose>
		<truncated>0</truncated>
		<difficult>0</difficult>
		<bndbox>
			<xmin>1033</xmin>
			<ymin>216</ymin>
			<xmax>1071</xmax>
			<ymax>244</ymax>
		</bndbox>
	</object>
	<object>
		<name>car</name>
		<pose>Unspecified</pose>
		<truncated>0</truncated>
		<difficult>0</difficult>
		<bndbox>
			<xmin>1010</xmin>
			<ymin>214</ymin>
			<xmax>1038</xmax>
			<ymax>239</ymax>
		</bndbox>
	</object>
	<object>
		<name>bus</name>
		<pose>Unspecified</pose>
		<truncated>0</truncated>
		<difficult>0</difficult>
		<bndbox>
			<xmin>940</xmin>
			<ymin>187</ymin>
			<xmax>1028</xmax>
			<ymax>239</ymax>
		</bndbox>
	</object>
	<object>
		<name>bus</name>
		<pose>Unspecified</pose>
		<truncated>0</truncated>
		<difficult>0</difficult>
		<bndbox>
			<xmin>125</xmin>
			<ymin>376</ymin>
			<xmax>210</xmax>
			<ymax>427</ymax>
		</bndbox>
	</object>
	<object>
		<name>bus</name>
		<pose>Unspecified</pose>
		<truncated>0</truncated>
		<difficult>0</difficult>
		<bndbox>
			<xmin>61</xmin>
			<ymin>376</ymin>
			<xmax>123</xmax>
			<ymax>420</ymax>
		</bndbox>
	</object>
	<object>
		<name>bus</name>
		<pose>Unspecified</pose>
		<truncated>0</truncated>
		<difficult>0</difficult>
		<bndbox>
			<xmin>137</xmin>
			<ymin>320</ymin>
			<xmax>201</xmax>
			<ymax>355</ymax>
		</bndbox>
	</object>
	<object>
		<name>car</name>
		<pose>Unspecified</pose>
		<truncated>0</truncated>
		<difficult>0</difficult>
		<bndbox>
			<xmin>282</xmin>
			<ymin>361</ymin>
			<xmax>328</xmax>
			<ymax>389</ymax>
		</bndbox>
	</object>
	<object>
		<name>car</name>
		<pose>Unspecified</pose>
		<truncated>0</truncated>
		<difficult>0</difficult>
		<bndbox>
			<xmin>345</xmin>
			<ymin>343</ymin>
			<xmax>397</xmax>
			<ymax>370</ymax>
		</bndbox>
	</object>
	<object>
		<name>car</name>
		<pose>Unspecified</pose>
		<truncated>0</truncated>
		<difficult>0</difficult>
		<bndbox>
			<xmin>321</xmin>
			<ymin>312</ymin>
			<xmax>382</xmax>
			<ymax>352</ymax>
		</bndbox>
	</object>
	<object>
		<name>car</name>
		<pose>Unspecified</pose>
		<truncated>0</truncated>
		<difficult>0</difficult>
		<bndbox>
			<xmin>482</xmin>
			<ymin>364</ymin>
			<xmax>549</xmax>
			<ymax>400</ymax>
		</bndbox>
	</object>
</annotation>
